{
  "id": "5e14bc72-c09a-462e-aa26-821b1921fdfa",
  "prevId": "00000000-0000-0000-0000-000000000000",
  "version": "7",
  "dialect": "postgresql",
  "tables": {
    "public.kyc_applications": {
      "name": "kyc_applications",
      "schema": "",
      "columns": {
        "id": {
          "name": "id",
          "type": "serial",
          "primaryKey": true,
          "notNull": true
        },
        "fullName": {
          "name": "fullName",
          "type": "varchar(128)",
          "primaryKey": false,
          "notNull": true
        },
        "email": {
          "name": "email",
          "type": "varchar(320)",
          "primaryKey": false,
          "notNull": true
        },
        "phone": {
          "name": "phone",
          "type": "varchar(32)",
          "primaryKey": false,
          "notNull": true
        },
        "country": {
          "name": "country",
          "type": "varchar(64)",
          "primaryKey": false,
          "notNull": true
        },
        "investmentAmount": {
          "name": "investmentAmount",
          "type": "varchar(32)",
          "primaryKey": false,
          "notNull": true
        },
        "investmentCurrency": {
          "name": "investmentCurrency",
          "type": "varchar(16)",
          "primaryKey": false,
          "notNull": true,
          "default": "'USDT'"
        },
        "walletAddress": {
          "name": "walletAddress",
          "type": "varchar(42)",
          "primaryKey": false,
          "notNull": true
        },
        "status": {
          "name": "status",
          "type": "kyc_status",
          "typeSchema": "public",
          "primaryKey": false,
          "notNull": true,
          "default": "'pending'"
        },
        "txHashKyc": {
          "name": "txHashKyc",
          "type": "varchar(66)",
          "primaryKey": false,
          "notNull": false
        },
        "txHashSender": {
          "name": "txHashSender",
          "type": "varchar(66)",
          "primaryKey": false,
          "notNull": false
        },
        "reviewNote": {
          "name": "reviewNote",
          "type": "text",
          "primaryKey": false,
          "notNull": false
        },
        "createdAt": {
          "name": "createdAt",
          "type": "timestamp",
          "primaryKey": false,
          "notNull": true,
          "default": "now()"
        },
        "updatedAt": {
          "name": "updatedAt",
          "type": "timestamp",
          "primaryKey": false,
          "notNull": true,
          "default": "now()"
        }
      },
      "indexes": {},
      "foreignKeys": {},
      "compositePrimaryKeys": {},
      "uniqueConstraints": {},
      "policies": {},
      "checkConstraints": {},
      "isRLSEnabled": false
    },
    "public.transactions": {
      "name": "transactions",
      "schema": "",
      "columns": {
        "id": {
          "name": "id",
          "type": "serial",
          "primaryKey": true,
          "notNull": true
        },
        "walletAddress": {
          "name": "walletAddress",
          "type": "varchar(42)",
          "primaryKey": false,
          "notNull": true
        },
        "txHash": {
          "name": "txHash",
          "type": "varchar(66)",
          "primaryKey": false,
          "notNull": true
        },
        "txType": {
          "name": "txType",
          "type": "tx_type",
          "typeSchema": "public",
          "primaryKey": false,
          "notNull": true
        },
        "amount": {
          "name": "amount",
          "type": "numeric(36, 18)",
          "primaryKey": false,
          "notNull": false
        },
        "tokenSymbol": {
          "name": "tokenSymbol",
          "type": "varchar(16)",
          "primaryKey": false,
          "notNull": false
        },
        "status": {
          "name": "status",
          "type": "tx_status",
          "typeSchema": "public",
          "primaryKey": false,
          "notNull": true,
          "default": "'pending'"
        },
        "blockNumber": {
          "name": "blockNumber",
          "type": "bigint",
          "primaryKey": false,
          "notNull": false
        },
        "gasUsed": {
          "name": "gasUsed",
          "type": "varchar(32)",
          "primaryKey": false,
          "notNull": false
        },
        "errorMessage": {
          "name": "errorMessage",
          "type": "text",
          "primaryKey": false,
          "notNull": false
        },
        "createdAt": {
          "name": "createdAt",
          "type": "timestamp",
          "primaryKey": false,
          "notNull": true,
          "default": "now()"
        },
        "confirmedAt": {
          "name": "confirmedAt",
          "type": "timestamp",
          "primaryKey": false,
          "notNull": false
        }
      },
      "indexes": {},
      "foreignKeys": {},
      "compositePrimaryKeys": {},
      "uniqueConstraints": {
        "transactions_txHash_unique": {
          "name": "transactions_txHash_unique",
          "nullsNotDistinct": false,
          "columns": [
            "txHash"
          ]
        }
      },
      "policies": {},
      "checkConstraints": {},
      "isRLSEnabled": false
    },
    "public.users": {
      "name": "users",
      "schema": "",
      "columns": {
        "id": {
          "name": "id",
          "type": "serial",
          "primaryKey": true,
          "notNull": true
        },
        "openId": {
          "name": "openId",
          "type": "varchar(64)",
          "primaryKey": false,
          "notNull": true
        },
        "name": {
          "name": "name",
          "type": "text",
          "primaryKey": false,
          "notNull": false
        },
        "email": {
          "name": "email",
          "type": "varchar(320)",
          "primaryKey": false,
          "notNull": false
        },
        "loginMethod": {
          "name": "loginMethod",
          "type": "varchar(64)",
          "primaryKey": false,
          "notNull": false
        },
        "role": {
          "name": "role",
          "type": "role",
          "typeSchema": "public",
          "primaryKey": false,
          "notNull": true,
          "default": "'user'"
        },
        "createdAt": {
          "name": "createdAt",
          "type": "timestamp",
          "primaryKey": false,
          "notNull": true,
          "default": "now()"
        },
        "updatedAt": {
          "name": "updatedAt",
          "type": "timestamp",
          "primaryKey": false,
          "notNull": true,
          "default": "now()"
        },
        "lastSignedIn": {
          "name": "lastSignedIn",
          "type": "timestamp",
          "primaryKey": false,
          "notNull": true,
          "default": "now()"
        }
      },
      "indexes": {},
      "foreignKeys": {},
      "compositePrimaryKeys": {},
      "uniqueConstraints": {
        "users_openId_unique": {
          "name": "users_openId_unique",
          "nullsNotDistinct": false,
          "columns": [
            "openId"
          ]
        }
      },
      "policies": {},
      "checkConstraints": {},
      "isRLSEnabled": false
    },
    "public.wallet_bindings": {
      "name": "wallet_bindings",
      "schema": "",
      "columns": {
        "id": {
          "name": "id",
          "type": "serial",
          "primaryKey": true,
          "notNull": true
        },
        "userId": {
          "name": "userId",
          "type": "integer",
          "primaryKey": false,
          "notNull": true
        },
        "walletAddress": {
          "name": "walletAddress",
          "type": "varchar(42)",
          "primaryKey": false,
          "notNull": true
        },
        "isPrimary": {
          "name": "isPrimary",
          "type": "boolean",
          "primaryKey": false,
          "notNull": true,
          "default": false
        },
        "createdAt": {
          "name": "createdAt",
          "type": "timestamp",
          "primaryKey": false,
          "notNull": true,
          "default": "now()"
        }
      },
      "indexes": {},
      "foreignKeys": {},
      "compositePrimaryKeys": {},
      "uniqueConstraints": {
        "wallet_bindings_walletAddress_unique": {
          "name": "wallet_bindings_walletAddress_unique",
          "nullsNotDistinct": false,
          "columns": [
            "walletAddress"
          ]
        }
      },
      "policies": {},
      "checkConstraints": {},
      "isRLSEnabled": false
    }
  },
  "enums": {
    "public.kyc_status": {
      "name": "kyc_status",
      "schema": "public",
      "values": [
        "pending",
        "approved",
        "rejected"
      ]
    },
    "public.role": {
      "name": "role",
      "schema": "public",
      "values": [
        "user",
        "admin"
      ]
    },
    "public.tx_status": {
      "name": "tx_status",
      "schema": "public",
      "values": [
        "pending",
        "confirmed",
        "failed"
      ]
    },
    "public.tx_type": {
      "name": "tx_type",
      "schema": "public",
      "values": [
        "stake",
        "unstake",
        "claim_reward",
        "claim_dividend",
        "purchase_private",
        "purchase_public",
        "approve",
        "whitelist"
      ]
    }
  },
  "schemas": {},
  "sequences": {},
  "roles": {},
  "policies": {},
  "views": {},
  "_meta": {
    "columns": {},
    "schemas": {},
    "tables": {}
  }
}